{
  "eurotile": {
    "an-nien": {
      "title": "An Niên",
      "brand": "Eurotile",
      "type": "tile_collection",
      "file": "data/collections/eurotile/an-nien.json",
      "product_codes": [
        "ANN G01",
        "ANN G02",
        "ANN G03",
        "ANN G04"
      ]
    },
    "cat-an": {
      "title": "Cát An",
      "brand": "Eurotile",
      "type": "tile_collection",
      "file": "data/collections/eurotile/cat-an.json",
      "product_codes": [
        "CAN X01M"
      ]
    },
    "cat-tuong": {
      "title": "Cát Tường",
      "brand": "Eurotile",
      "type": "tile_collection",
      "file": "data/collections/eurotile/cat-tuong.json",
      "product_codes": [
        "CAT S01G"
      ]
    },
    "chau-sa": {
      "title": "Châu Sa",
      "brand": "Eurotile",
      "type": "tile_collection",
      "file": "data/collections/eurotile/chau-sa.json",
      "product_codes": [
        "CHS G01 TF",
        "CHS L01 TF"
      ]
    },
    "chay-ve-mien-yen": {
      "title": "Chảy về miền yên",
      "brand": "Eurotile",
      "type": "tile_collection",
      "file": "data/collections/eurotile/chay-ve-mien-yen.json",
      "product_codes": [
        "CVM Q01TF"
      ]
    },
    "chi-giao-2": {
      "title": "Chi Giao",
      "brand": "Eurotile",
      "type": "tile_collection",
      "file": "data/collections/eurotile/chi-giao-2.json",
      "product_codes": [
        "CHG S01P",
        "CHG S01H"
      ]
    },
    "chi-giao": {
      "title": "Chi Giao",
      "brand": "Eurotile",
      "type": "tile_collection",
      "file": "data/collections/eurotile/chi-giao.json",
      "product_codes": [
        "SIG. CHG Q01",
        "SIG.CHG E01"
      ]
    },
    "chieu-nien": {
      "title": "Chiêu Niên",
      "brand": "Eurotile",
      "type": "tile_collection",
      "file": "data/collections/eurotile/chieu-nien.json",
      "product_codes": [
        "CHN X01C"
      ]
    },
    "chieu-phong": {
      "title": "Chiêu Phong",
      "brand": "Eurotile",
      "type": "tile_collection",
      "file": "data/collections/eurotile/chieu-phong.json",
      "product_codes": [
        "SIG. P8806",
        "SIG. P4806",
        "SIG. P61206"
      ]
    },
    "dan-chau": {
      "title": "Đan Châu",
      "brand": "Eurotile",
      "type": "tile_collection",
      "file": "data/collections/eurotile/dan-chau.json",
      "product_codes": [
        "DAC Q01 TF",
        "DAC Q02 TF",
        "DAC Q03 TF"
      ]
    },
    "dang-nguyen": {
      "title": "Đăng Nguyên",
      "brand": "Eurotile",
      "type": "tile_collection",
      "file": "data/collections/eurotile/dang-nguyen.json",
      "product_codes": [
        "DAN N01P"
      ]
    },
    "dang-son": {
      "title": "Đăng Sơn",
      "brand": "Eurotile",
      "type": "tile_collection",
      "file": "data/collections/eurotile/dang-son.json",
      "product_codes": [
        "DAS QO1",
        "DAS QO2",
        "DAS DO1",
        "DAS DO2"
      ]
    },
    "denim-2": {
      "title": "Denim",
      "brand": "Eurotile",
      "type": "tile_collection",
      "file": "data/collections/eurotile/denim-2.json",
      "product_codes": [
        "DNI S01P"
      ]
    },
    "denim": {
      "title": "Denim",
      "brand": "Eurotile",
      "type": "tile_collection",
      "file": "data/collections/eurotile/denim.json",
      "product_codes": [
        "SIG.DNI Q01",
        "SIG. DNI E01"
      ]
    },
    "dien-vien": {
      "title": "Điền Viên",
      "brand": "Eurotile",
      "type": "tile_collection",
      "file": "data/collections/eurotile/dien-vien.json",
      "product_codes": [
        "DVI CO1 TF",
        "DVI CO2 TF"
      ]
    },
    "diep-vu": {
      "title": "Diệp Vũ",
      "brand": "Eurotile",
      "type": "tile_collection",
      "file": "data/collections/eurotile/diep-vu.json",
      "product_codes": [
        "DIV G01 TF"
      ]
    },
    "dong-phong": {
      "title": "Đông Phong",
      "brand": "Eurotile",
      "type": "tile_collection",
      "file": "data/collections/eurotile/dong-phong.json",
      "product_codes": [
        "SIG. P8804"
      ]
    },
    "dong-phuong": {
      "title": "Đông Phương",
      "brand": "Eurotile",
      "type": "tile_collection",
      "file": "data/collections/eurotile/dong-phuong.json",
      "product_codes": [
        "DOP S01G"
      ]
    },
    "du-phong": {
      "title": "Du Phong",
      "brand": "Eurotile",
      "type": "tile_collection",
      "file": "data/collections/eurotile/du-phong.json",
      "product_codes": [
        "SIG. P8807",
        "SIG. P4807",
        "SIG. P61207"
      ]
    },
    "duoi-tan-la": {
      "title": "Dưới tán lá",
      "brand": "Eurotile",
      "type": "tile_collection",
      "file": "data/collections/eurotile/duoi-tan-la.json",
      "product_codes": [
        "DTL Q01TF"
      ]
    },
    "giai-ky": {
      "title": "Giai Kỳ",
      "brand": "Eurotile",
      "type": "tile_collection",
      "file": "data/collections/eurotile/giai-ky.json",
      "product_codes": [
        "GIK X01P",
        "GIK S01G"
      ]
    },
    "gibellina": {
      "title": "Gibellina",
      "brand": "Eurotile",
      "type": "tile_collection",
      "file": "data/collections/eurotile/gibellina.json",
      "product_codes": [
        "GIB20 G02",
        "GIB20 G03",
        "GIB20 G04",
        "GIB20 H03",
        "GIB20 H04"
      ]
    },
    "hai-bang": {
      "title": "Hải Băng",
      "brand": "Eurotile",
      "type": "tile_collection",
      "file": "data/collections/eurotile/hai-bang.json",
      "product_codes": [
        "HAB S01P",
        "HAB S02P"
      ]
    },
    "hai-luu": {
      "title": "Hải Lưu",
      "brand": "Eurotile",
      "type": "tile_collection",
      "file": "data/collections/eurotile/hai-luu.json",
      "product_codes": [
        "HAL X01M"
      ]
    },
    "hai-phong-1": {
      "title": "Hải Phong",
      "brand": "Eurotile",
      "type": "tile_collection",
      "file": "data/collections/eurotile/hai-phong-1.json",
      "product_codes": [
        "HAP N01P"
      ]
    },
    "hai-phong": {
      "title": "Hải Phong",
      "brand": "Eurotile",
      "type": "tile_collection",
      "file": "data/collections/eurotile/hai-phong.json",
      "product_codes": [
        "SIG. P4801",
        "SIG. P8801",
        "SIG. P61201"
      ]
    },
    "hai-thuy": {
      "title": "Hải Thụy",
      "brand": "Eurotile",
      "type": "tile_collection",
      "file": "data/collections/eurotile/hai-thuy.json",
      "product_codes": [
        "HAT I01",
        "HAT I02"
      ]
    },
    "hanh-trinh-phu-sa": {
      "title": "Hành trình phù sa",
      "brand": "Eurotile",
      "type": "tile_collection",
      "file": "data/collections/eurotile/hanh-trinh-phu-sa.json",
      "product_codes": [
        "HTP Q01TF"
      ]
    },
    "hoa-da": {
      "title": "Hoa Đá",
      "brand": "Eurotile",
      "type": "tile_collection",
      "file": "data/collections/eurotile/hoa-da.json",
      "product_codes": [
        "HOD D01",
        "HOD D02",
        "HOD D03",
        "HOD D04",
        "HOD G01",
        "HOD G02",
        "HOD G03",
        "HOD G04"
      ]
    },
    "hoa-trong-gio-lang": {
      "title": "Hoa trong gió lặng",
      "brand": "Eurotile",
      "type": "tile_collection",
      "file": "data/collections/eurotile/hoa-trong-gio-lang.json",
      "product_codes": [
        "HTG Q01TF"
      ]
    },
    "hoa-vien": {
      "title": "Hoa Viên",
      "brand": "Eurotile",
      "type": "tile_collection",
      "file": "data/collections/eurotile/hoa-vien.json",
      "product_codes": [
        "HOV C02 TF"
      ]
    },
    "hoi-an": {
      "title": "Hội An",
      "brand": "Eurotile",
      "type": "tile_collection",
      "file": "data/collections/eurotile/hoi-an.json",
      "product_codes": [
        "HOA Q01",
        "HOA Q02",
        "HOA E01",
        "HOA E02"
      ]
    },
    "huyen-sa": {
      "title": "Huyền Sa",
      "brand": "Eurotile",
      "type": "tile_collection",
      "file": "data/collections/eurotile/huyen-sa.json",
      "product_codes": [
        "HUS G01 TF",
        "HUS L01 TF"
      ]
    },
    "khai-ca": {
      "title": "Khải Ca",
      "brand": "Eurotile",
      "type": "tile_collection",
      "file": "data/collections/eurotile/khai-ca.json",
      "product_codes": [
        "SIG.KHC Q01S",
        "SIG.KHC Q02S",
        "SIG.KHC E01S",
        "SIG.KHC E02S"
      ]
    },
    "khai-dang": {
      "title": "Khải Đăng",
      "brand": "Eurotile",
      "type": "tile_collection",
      "file": "data/collections/eurotile/khai-dang.json",
      "product_codes": [
        "KHD S02H",
        "KHD S02P"
      ]
    },
    "khoi-nguyen": {
      "title": "Khởi Nguyên",
      "brand": "Eurotile",
      "type": "tile_collection",
      "file": "data/collections/eurotile/khoi-nguyen.json",
      "product_codes": [
        "KHN X01M",
        "KHN X02M",
        "KHN X01P"
      ]
    },
    "khuc-vang": {
      "title": "Khúc vàng",
      "brand": "Eurotile",
      "type": "tile_collection",
      "file": "data/collections/eurotile/khuc-vang.json",
      "product_codes": [
        "KHV Q01TF"
      ]
    },
    "ky-uc-so": {
      "title": "Ký ức số",
      "brand": "Eurotile",
      "type": "tile_collection",
      "file": "data/collections/eurotile/ky-uc-so.json",
      "product_codes": [
        "KUS Q01TF"
      ]
    },
    "lam-hai": {
      "title": "Lam Hải",
      "brand": "Eurotile",
      "type": "tile_collection",
      "file": "data/collections/eurotile/lam-hai.json",
      "product_codes": [
        "LAH I01",
        "LAH I02",
        "LAH I04",
        "LAH I05"
      ]
    },
    "lan-ha": {
      "title": "Lan Hạ",
      "brand": "Eurotile",
      "type": "tile_collection",
      "file": "data/collections/eurotile/lan-ha.json",
      "product_codes": [
        "LHA X01M"
      ]
    },
    "liguria": {
      "title": "Liguria",
      "brand": "Eurotile",
      "type": "tile_collection",
      "file": "data/collections/eurotile/liguria.json",
      "product_codes": [
        "LIG20 G01",
        "LIG20 G02",
        "LIG20 H01",
        "LIG20 H02"
      ]
    },
    "luu-sa": {
      "title": "Lưu Sa",
      "brand": "Eurotile",
      "type": "tile_collection",
      "file": "data/collections/eurotile/luu-sa.json",
      "product_codes": [
        "LUS H01",
        "LUS H02",
        "LUS H03",
        "LUS G01",
        "LUS G02",
        "LUS G03",
        "LUS G04"
      ]
    },
    "luu-thuy": {
      "title": "Lưu Thủy",
      "brand": "Eurotile",
      "type": "tile_collection",
      "file": "data/collections/eurotile/luu-thuy.json",
      "product_codes": [
        "LTH D01",
        "LTH D02",
        "LTH D03",
        "LTH D04",
        "LTH D05",
        "LTH G01",
        "LTH G02"
      ]
    },
    "moc-binh-1": {
      "title": "Mộc Bình",
      "brand": "Eurotile",
      "type": "tile_collection",
      "file": "data/collections/eurotile/moc-binh-1.json",
      "product_codes": [
        "MOB M01",
        "MOB M02",
        "MOB M03"
      ]
    },
    "moc-chau": {
      "title": "Mộc Châu",
      "brand": "Eurotile",
      "type": "tile_collection",
      "file": "data/collections/eurotile/moc-chau.json",
      "product_codes": [
        "MOC D01",
        "MOC D02",
        "MOC D03",
        "MOC D04",
        "MOC M01",
        "MOC M02",
        "MOC M03",
        "MOC M04"
      ]
    },
    "moc-chi": {
      "title": "Mộc Chi",
      "brand": "Eurotile",
      "type": "tile_collection",
      "file": "data/collections/eurotile/moc-chi.json",
      "product_codes": [
        "MCH M01",
        "MCH M02",
        "MCH M03"
      ]
    },
    "moc-lan": {
      "title": "Mộc Lan",
      "brand": "Eurotile",
      "type": "tile_collection",
      "file": "data/collections/eurotile/moc-lan.json",
      "product_codes": [
        "MOL K01",
        "MOL K02",
        "MOL K03",
        "MOL K04",
        "MOL I01",
        "MOL I02",
        "MOL I03",
        "MOL I04",
        "MOL I05",
        "MOL M01",
        "MOL M02",
        "MOL M03",
        "MOL M04"
      ]
    },
    "moc-mien": {
      "title": "Mộc Miên",
      "brand": "Eurotile",
      "type": "tile_collection",
      "file": "data/collections/eurotile/moc-mien.json",
      "product_codes": [
        "MMI M01",
        "MMI M02",
        "MMI M03",
        "MMI M04",
        "MMI M05",
        "MMI K01",
        "MMI K02",
        "MMI K03",
        "MMI K05",
        "MMI Z05 MR4"
      ]
    },
    "moc-tra": {
      "title": "Mộc Trà",
      "brand": "Eurotile",
      "type": "tile_collection",
      "file": "data/collections/eurotile/moc-tra.json",
      "product_codes": [
        "MTR A01C",
        "MTR A02C",
        "MTR A03C"
      ]
    },
    "moc-tung": {
      "title": "Mộc Tùng",
      "brand": "Eurotile",
      "type": "tile_collection",
      "file": "data/collections/eurotile/moc-tung.json",
      "product_codes": [
        "MTU M01",
        "MTU M02",
        "MTU M03"
      ]
    },
    "nam-giao": {
      "title": "Nam Giao",
      "brand": "Eurotile",
      "type": "tile_collection",
      "file": "data/collections/eurotile/nam-giao.json",
      "product_codes": [
        "NAG N01P"
      ]
    },
    "ngoc-giao-1": {
      "title": "Ngọc Giao",
      "brand": "Eurotile",
      "type": "tile_collection",
      "file": "data/collections/eurotile/ngoc-giao-1.json",
      "product_codes": [
        "SIG.NGG Q04P",
        "SIG.NGG E04P"
      ]
    },
    "ngoc-giao": {
      "title": "Ngọc Giao",
      "brand": "Eurotile",
      "type": "tile_collection",
      "file": "data/collections/eurotile/ngoc-giao.json",
      "product_codes": [
        "NGG S04P",
        "NGG S04H"
      ]
    },
    "ngoc-trai": {
      "title": "Ngọc Trai",
      "brand": "Eurotile",
      "type": "tile_collection",
      "file": "data/collections/eurotile/ngoc-trai.json",
      "product_codes": [
        "NGT N01P"
      ]
    },
    "nguyet-cat": {
      "title": "Nguyệt Cát",
      "brand": "Eurotile",
      "type": "tile_collection",
      "file": "data/collections/eurotile/nguyet-cat.json",
      "product_codes": [
        "NGC H01",
        "NGC H02",
        "NGC H03",
        "NGC H04",
        "NGC D01",
        "NGC D02",
        "NGC D03",
        "NGC D04",
        "NGC I01",
        "NGC I02",
        "NGC I03",
        "NGC I04"
      ]
    },
    "nguyet-phong": {
      "title": "Nguyệt Phong",
      "brand": "Eurotile",
      "type": "tile_collection",
      "file": "data/collections/eurotile/nguyet-phong.json",
      "product_codes": [
        "SIG. P8802"
      ]
    },
    "nha-ca-1": {
      "title": "Nhã Ca",
      "brand": "Eurotile",
      "type": "tile_collection",
      "file": "data/collections/eurotile/nha-ca-1.json",
      "product_codes": [
        "NHC S01H",
        "NHC S02M",
        "NHC S03H",
        "NHC S04M",
        "NHC S05M"
      ]
    },
    "nha-ca": {
      "title": "Nhã Ca",
      "brand": "Eurotile",
      "type": "tile_collection",
      "file": "data/collections/eurotile/nha-ca.json",
      "product_codes": [
        "SIG.NHC Q05S",
        "SIG.NHC Q06S",
        "SIG.NHC E05S",
        "SIG.NHC E06S"
      ]
    },
    "nha-vi": {
      "title": "Nhã Vi",
      "brand": "Eurotile",
      "type": "tile_collection",
      "file": "data/collections/eurotile/nha-vi.json",
      "product_codes": [
        "SIG.NHV E01",
        "SIG.NHV Q01"
      ]
    },
    "nhat-nguyet": {
      "title": "Nhật Nguyệt",
      "brand": "Eurotile",
      "type": "tile_collection",
      "file": "data/collections/eurotile/nhat-nguyet.json",
      "product_codes": [
        "NHN G01 TF",
        "NHN G02 TF",
        "NHN L01 TF",
        "NHN L02 TF"
      ]
    },
    "phong-lan": {
      "title": "Phong Lan",
      "brand": "Eurotile",
      "type": "tile_collection",
      "file": "data/collections/eurotile/phong-lan.json",
      "product_codes": [
        "PLA S01P",
        "PLA S01H"
      ]
    },
    "phong-luu-1": {
      "title": "Phong Lưu",
      "brand": "Eurotile",
      "type": "tile_collection",
      "file": "data/collections/eurotile/phong-luu-1.json",
      "product_codes": [
        "PHL S01P"
      ]
    },
    "phong-luu": {
      "title": "Phong Lưu",
      "brand": "Eurotile",
      "type": "tile_collection",
      "file": "data/collections/eurotile/phong-luu.json",
      "product_codes": [
        "SIG. P8803"
      ]
    },
    "phu-quy": {
      "title": "Phú Quý",
      "brand": "Eurotile",
      "type": "tile_collection",
      "file": "data/collections/eurotile/phu-quy.json",
      "product_codes": [
        "PHQ G01 TF",
        "PHQ G02 TF",
        "PHQ G03 TF",
        "PHQ L01 TF",
        "PHQ L02 TF",
        "PHQ L03 TF"
      ]
    },
    "phu-sa": {
      "title": "Phù Sa",
      "brand": "Eurotile",
      "type": "tile_collection",
      "file": "data/collections/eurotile/phu-sa.json",
      "product_codes": [
        "PHS I01",
        "PHS I02",
        "PHS I03",
        "PHS G01",
        "PHS G02",
        "PHS G03",
        "PHS Q01",
        "PHS Q02"
      ]
    },
    "pompeii": {
      "title": "Pompeii",
      "brand": "Eurotile",
      "type": "tile_collection",
      "file": "data/collections/eurotile/pompeii.json",
      "product_codes": [
        "POM20 G01",
        "POM20 G02",
        "POM20 H01",
        "POM20 H02"
      ]
    },
    "sa-thach": {
      "title": "Sa Thạch",
      "brand": "Eurotile",
      "type": "tile_collection",
      "file": "data/collections/eurotile/sa-thach.json",
      "product_codes": [
        "SAT H01",
        "SAT H02",
        "SAT H03",
        "SAT G01",
        "SAT G02",
        "SAT G03"
      ]
    },
    "son-du": {
      "title": "Sơn Du",
      "brand": "Eurotile",
      "type": "tile_collection",
      "file": "data/collections/eurotile/son-du.json",
      "product_codes": [
        "SOD N01P",
        "SOD N01H"
      ]
    },
    "son-khue": {
      "title": "Sơn Khuê",
      "brand": "Eurotile",
      "type": "tile_collection",
      "file": "data/collections/eurotile/son-khue.json",
      "product_codes": [
        "SOK Q01",
        "SOK Q02",
        "SOK Q03",
        "SOK Q04",
        "SOK E01",
        "SOK E02",
        "SOK E03",
        "SOK E04",
        "SOK I01",
        "SOK I03"
      ]
    },
    "song-bang": {
      "title": "Sông Băng",
      "brand": "Eurotile",
      "type": "tile_collection",
      "file": "data/collections/eurotile/song-bang.json",
      "product_codes": [
        "SIG.SOB Q01",
        "SIG.SOB E01"
      ]
    },
    "thach-an": {
      "title": "Thạch An",
      "brand": "Eurotile",
      "type": "tile_collection",
      "file": "data/collections/eurotile/thach-an.json",
      "product_codes": [
        "THA X01C"
      ]
    },
    "thach-khue": {
      "title": "Thạch Khuê",
      "brand": "Eurotile",
      "type": "tile_collection",
      "file": "data/collections/eurotile/thach-khue.json",
      "product_codes": [
        "THK H01",
        "THK H02",
        "THK G01",
        "THK G02"
      ]
    },
    "thach-nhien": {
      "title": "Thạch Nhiên",
      "brand": "Eurotile",
      "type": "tile_collection",
      "file": "data/collections/eurotile/thach-nhien.json",
      "product_codes": [
        "THN X01C"
      ]
    },
    "thach-son": {
      "title": "Thạch Sơn",
      "brand": "Eurotile",
      "type": "tile_collection",
      "file": "data/collections/eurotile/thach-son.json",
      "product_codes": [
        "THS S01P"
      ]
    },
    "thach-vu": {
      "title": "Thạch Vũ",
      "brand": "Eurotile",
      "type": "tile_collection",
      "file": "data/collections/eurotile/thach-vu.json",
      "product_codes": [
        "THV Q01",
        "THV Q02",
        "THV Q03"
      ]
    },
    "thanh-mai": {
      "title": "Thanh Mai",
      "brand": "Eurotile",
      "type": "tile_collection",
      "file": "data/collections/eurotile/thanh-mai.json",
      "product_codes": [
        "THM N01P"
      ]
    },
    "thanh-tam-1": {
      "title": "Thanh Tâm",
      "brand": "Eurotile",
      "type": "tile_collection",
      "file": "data/collections/eurotile/thanh-tam-1.json",
      "product_codes": [
        "THT S04P"
      ]
    },
    "thanh-tam": {
      "title": "Thanh Tâm",
      "brand": "Eurotile",
      "type": "tile_collection",
      "file": "data/collections/eurotile/thanh-tam.json",
      "product_codes": [
        "SIG.THT E01",
        "SIG.THT Q01"
      ]
    },
    "thien-di": {
      "title": "Thiên Di",
      "brand": "Eurotile",
      "type": "tile_collection",
      "file": "data/collections/eurotile/thien-di.json",
      "product_codes": [
        "THD H02",
        "THD H03",
        "THD G02",
        "THD G03",
        "THD G04",
        "THD G05"
      ]
    },
    "thiet-thach": {
      "title": "Thiết Thạch",
      "brand": "Eurotile",
      "type": "tile_collection",
      "file": "data/collections/eurotile/thiet-thach.json",
      "product_codes": [
        "TTH N01P"
      ]
    },
    "thoang-tay-nguyen": {
      "title": "Thoáng tây nguyên",
      "brand": "Eurotile",
      "type": "tile_collection",
      "file": "data/collections/eurotile/thoang-tay-nguyen.json",
      "product_codes": [
        "TTN Q01TF"
      ]
    },
    "thu-phong": {
      "title": "Thu Phong",
      "brand": "Eurotile",
      "type": "tile_collection",
      "file": "data/collections/eurotile/thu-phong.json",
      "product_codes": [
        "THP S01M"
      ]
    },
    "thuy-phong": {
      "title": "Thụy Phong",
      "brand": "Eurotile",
      "type": "tile_collection",
      "file": "data/collections/eurotile/thuy-phong.json",
      "product_codes": [
        "SIG. P8805",
        "SIG. P4805",
        "SIG. P61205"
      ]
    },
    "trang-an": {
      "title": "Tràng An",
      "brand": "Eurotile",
      "type": "tile_collection",
      "file": "data/collections/eurotile/trang-an.json",
      "product_codes": [
        "TRA Q02",
        "TRA Q04",
        "TRA E02",
        "TRA E04",
        "TRA E03",
        "TRA E03P"
      ]
    },
    "tuyet-san": {
      "title": "Tuyết San",
      "brand": "Eurotile",
      "type": "tile_collection",
      "file": "data/collections/eurotile/tuyet-san.json",
      "product_codes": [
        "SIG. TSA Q01"
      ]
    },
    "van-du": {
      "title": "Vân Du",
      "brand": "Eurotile",
      "type": "tile_collection",
      "file": "data/collections/eurotile/van-du.json",
      "product_codes": [
        "VAD Z01 MH1"
      ]
    },
    "vong-cat": {
      "title": "Vọng Cát",
      "brand": "Eurotile",
      "type": "tile_collection",
      "file": "data/collections/eurotile/vong-cat.json",
      "product_codes": [
        "VOC H01",
        "VOC H02",
        "VOC H03",
        "VOC H04",
        "VOC H05",
        "VOC G01",
        "VOC G02",
        "VOC G03",
        "VOC G04",
        "VOC G05",
        "VOC Z123 MG2"
      ]
    },
    "vu-dieu-xanh": {
      "title": "Vũ điệu xanh",
      "brand": "Eurotile",
      "type": "tile_collection",
      "file": "data/collections/eurotile/vu-dieu-xanh.json",
      "product_codes": [
        "VDX Q01TF"
      ]
    },
    "vu-khuc": {
      "title": "Vũ Khúc",
      "brand": "Eurotile",
      "type": "tile_collection",
      "file": "data/collections/eurotile/vu-khuc.json",
      "product_codes": [
        "VUK X01P",
        "VUK S01G"
      ]
    },
    "yen-minh": {
      "title": "Yên Minh",
      "brand": "Eurotile",
      "type": "tile_collection",
      "file": "data/collections/eurotile/yen-minh.json",
      "product_codes": [
        "YMI S02M",
        "YMI S04M"
      ]
    }
  }
}
