{
  "title": "VBS 305",
  "product_info": {
    "Mã sản phẩm": "VBS 305",
    "Hãng sản xuất": "Viglacera",
    "Giá": "Liên hệ",
    "Kích thước": "30x30 cm",
    "Xương": "Semi Porcelain",
    "Bề mặt": "Matt",
    "Nguồn dữ liệu": "Viglacera Tiles",
    "URL": "https://viglaceratiles.vn/san-pham/gach-op-lat/san-pham-khac/vbs-305.html"
  },
  "description": "VBS 305",
  "images": [
    "https://viglaceratiles.vn/pictures/files/3-sanpham/gachoplat/san-pham-khac/vbs301/vbs305.jpg"
  ],
  "view_count": 0
}
