{
  "title": "Sahara Noir",
  "product_info": {
    "Mã sản phẩm": "Sahara Noir",
    "Loại sản phẩm": "Đá nung kết / tấm lớn",
    "Hãng sản xuất": "Vasta Stone",
    "Giá": "Liên hệ",
    "Nguồn dữ liệu": "Vasta Stone",
    "URL": "https://vastastone.com/vi/collection/sahara-noir/"
  },
  "description": "Đá cẩm thạch đen bóng mượt tạo sự kết nối giữa cái cũ và cái mới mà không gây ảnh hưởng lẫn nhau. Bề mặt họa tiết gắn kết sự đồng nhất và mâu thuẫn tự nhiên, tạo nên cảm giác chiều sâu và trật tự cho tổng thể.\n\nSIZES 160×320 cm BỀ MẶT MỜ MỊN BÓNG ĐỘ DÀY 6mm 12mm 20mm\n\nWorking on something big? We collaborate with architects, designers and dreamers—get in touch!",
  "images": [
    "https://vastastone.com/wp-content/uploads/2023/03/detail-1-2.jpg",
    "https://vastastone.com/wp-content/uploads/2023/03/detail-5.jpg",
    "https://vastastone.com/wp-content/uploads/2023/02/SIZE-2-173x300.png",
    "https://vastastone.com/wp-content/uploads/2023/02/SIZE-2.png"
  ],
  "view_count": 0
}
